skills/elo.py
skills/factorgraph.py
skills/glicko.py
skills/matrix.py
skills/numerics.py
skills/__init__.py
skills/testsuite/test_elo.py
skills/testsuite/test_glicko.py
skills/testsuite/test_numerics.py
skills/testsuite/__init__.py
skills/testsuite/trueskill/test_factorgraph.py
skills/testsuite/trueskill/test_twoplayer.py
skills/testsuite/trueskill/test_twoteam.py
skills/testsuite/trueskill/__init__.py
skills/trueskill/factors.py
skills/trueskill/layers.py
skills/trueskill/truncated.py
skills/trueskill/__init__.py
skills-0.3.0.dist-info/DESCRIPTION.rst
skills-0.3.0.dist-info/METADATA
skills-0.3.0.dist-info/metadata.json
skills-0.3.0.dist-info/RECORD
skills-0.3.0.dist-info/top_level.txt
skills-0.3.0.dist-info/WHEEL
