Metadata-Version: 1.1
Name: skills
Version: 0.3.0
Summary: Implementation of the TrueSkill, Glicko and Elo Ranking Algorithms
Home-page: http://github.com/McLeopold/PythonSkills/
Author: Scott Hamilton
Author-email: mcleopold@gmail.com
License: BSD
Keywords: skill trueskill glicko elo
Platform: UNKNOWN
Classifier: Programming Language :: Python
Classifier: Programming Language :: Python :: 2
Classifier: Programming Language :: Python :: 3
Classifier: License :: OSI Approved :: BSD License
Classifier: Operating System :: OS Independent
Classifier: Development Status :: 5 - Production/Stable
Classifier: Environment :: Other Environment
Classifier: Intended Audience :: Developers
Classifier: Intended Audience :: Science/Research
Classifier: Topic :: Games/Entertainment
Classifier: Topic :: Scientific/Engineering :: Mathematics
Classifier: Topic :: Software Development :: Libraries :: Python Modules
